strava_activity_mcp_server/__init__.py
strava_activity_mcp_server/__main__.py
strava_activity_mcp_server/strava_activity_mcp_server.py
strava_activity_mcp_server-0.3.2.dist-info/METADATA
strava_activity_mcp_server-0.3.2.dist-info/WHEEL
strava_activity_mcp_server-0.3.2.dist-info/entry_points.txt
strava_activity_mcp_server-0.3.2.dist-info/licenses/LICENSE
strava_activity_mcp_server-0.3.2.dist-info/RECORD
