Metadata-Version: 2.4
Name: strava-activity-mcp-server
Version: 0.3.2
Summary: Strava MCP server: one-time browser auth, then automatic refresh-token login
License-File: LICENSE
Requires-Python: >=3.10
Requires-Dist: build>=1.3.0
Requires-Dist: mcp[cli]>=1.16.0
Requires-Dist: twine>=6.2.0
